promweaver/__init__.py
promweaver/bc_provider.py
promweaver/compute_bc.py
promweaver/cone_prom_bc.py
promweaver/iso_prom.py
promweaver/j_prom_bc.py
promweaver/limb_darkening.py
promweaver/pctr_prom.py
promweaver/prom_bc.py
promweaver/prom_compatible_bc.py
promweaver/prom_model.py
promweaver/stratified_prom.py
promweaver/utils.py
promweaver/version.py
promweaver-0.5.2.dist-info/licenses/LICENSE
promweaver-0.5.2.dist-info/METADATA
promweaver-0.5.2.dist-info/WHEEL
promweaver-0.5.2.dist-info/top_level.txt
promweaver-0.5.2.dist-info/RECORD
