Metadata-Version: 2.4
Name: promweaver
Version: 0.5.2
Summary: Prominence/Filament Radiative Transfer Modelling with Lightweaver
Home-page: http://github.com/Goobley/Promweaver
Author: Chris Osborne
Author-email: christopher.osborne@glasgow.ac.uk
License: MIT
Requires-Python: >=3.8
License-File: LICENSE
Requires-Dist: lightweaver>=0.8.0rc6
Dynamic: author
Dynamic: author-email
Dynamic: description
Dynamic: description-content-type
Dynamic: home-page
Dynamic: license
Dynamic: license-file
Dynamic: requires-dist
Dynamic: requires-python
Dynamic: summary
